claude_vault/__init__.py
claude_vault/cli.py
claude_vault/code_parser.py
claude_vault/config.py
claude_vault/markdown.py
claude_vault/models.py
claude_vault/parser.py
claude_vault/state.py
claude_vault/sync.py
claude_vault/tagging.py
claude_vault-0.4.1.dist-info/METADATA
claude_vault-0.4.1.dist-info/WHEEL
claude_vault-0.4.1.dist-info/entry_points.txt
claude_vault-0.4.1.dist-info/top_level.txt
claude_vault-0.4.1.dist-info/RECORD
