Metadata-Version: 2.4
Name: claude-vault
Version: 0.4.1
Summary: Sync Claude conversations to Obsidian markdown files
Author: Mario Padilla
License: AGPL-3.0-or-later OR Commercial
Keywords: claude,obsidian,markdown,sync,ai,conversations
Requires-Python: >=3.9
Requires-Dist: typer[all]>=0.9.0
Requires-Dist: pydantic>=2.0.0
Requires-Dist: python-frontmatter>=1.0.0
Requires-Dist: rich>=13.0.0
Requires-Dist: requests>=2.31.0
Provides-Extra: dev
Requires-Dist: pytest>=7.4.0; extra == "dev"
Requires-Dist: ruff>=0.1.9; extra == "dev"
Requires-Dist: mypy>=1.8.0; extra == "dev"
Requires-Dist: pre-commit>=3.5.0; extra == "dev"
Requires-Dist: types-requests>=2.31.0; extra == "dev"
